.gitignore
CHANGES.txt
LICENSE.txt
MANIFEST.in
README.txt
setup.py
Pyng.egg-info/PKG-INFO
Pyng.egg-info/SOURCES.txt
Pyng.egg-info/dependency_links.txt
Pyng.egg-info/entry_points.txt
Pyng.egg-info/top_level.txt
pyng/ProgressBar.py
pyng/ProgressMeter.py
pyng/__init__.py
pyng/args.py
pyng/commands.py
pyng/deco.py
pyng/descrs.py
pyng/dicts.py
pyng/exc.py
pyng/exc3.py
pyng/file_arg.py
pyng/find.py
pyng/funcs.py
pyng/genio.py
pyng/graph.py
pyng/iters.py
pyng/janitor.py
pyng/logs.py
pyng/methods.py
pyng/out.py
pyng/path.py
pyng/pickles.py
pyng/relwalk.py
pyng/replacefile.py
pyng/throttle.py
pyng/timing.py
pyng/toposort.py
pyng/test/__init__.py
pyng/test/test_deco.py
pyng/test/test_exc.py
pyng/test/test_genio.py
pyng/test/test_iters.py
pyng/test/test_out.py
pyng/test/test_relwalk.py
pyng/test/test_replacefile.py
pyng/tk/FitText.py
pyng/tk/__init__.py
pyng/tk/form.py
pyng/tk/getpw.py
pyng/tk/multistatus.py
pyng/tk/popup.py
pyng/tk/printwindow.py