Metadata-Version: 2.1
Name: Pyng
Version: 1.6.2
Summary: Yet another collection of Python utility functions
Home-page: https://pypi.org/project/Pyng/
Author: Nat Goodspeed
Author-email: nat.cognitoy@gmail.com
License: LICENSE.txt
License-File: LICENSE.txt
